mercury_api_client-0.1.0.dist-info/licenses/LICENSE
mercury_client/__init__.py
mercury_client/async_client.py
mercury_client/client.py
mercury_client/py.typed
mercury_api_client-0.1.0.dist-info/METADATA
mercury_api_client-0.1.0.dist-info/WHEEL
mercury_api_client-0.1.0.dist-info/top_level.txt
mercury_api_client-0.1.0.dist-info/RECORD
